{
	"beach": "http://i.imgur.com/BU4ooId.jpg",
	"big_shop": "http://i.imgur.com/wvgxiDv.jpg",
	"bryant_park": "http://i.imgur.com/T7NZ2jO.jpg",
	"gasstation": "http://i.imgur.com/i8TmCVn.jpg",
	"greenfield": "http://i.imgur.com/Km7bVli.jpg",
	"hangar": "http://i.imgur.com/S9EgIZk.jpg",
	"ibl": "http://i.imgur.com/0mGEGWO.jpg",
	"industrial": "http://i.imgur.com/1JQGDNW.jpg",
	"industrial2_sunset": "http://i.imgur.com/eHuSGTG.jpg",
	"kunos": "http://i.imgur.com/5u4QI3R.jpg",
	"nightlife": "http://i.imgur.com/oR68AeI.jpg",
	"parkinglot-1": "http://i.imgur.com/Iglu3FQ.jpg",
	"parkinglot-2": "http://i.imgur.com/udz2wCu.jpg",
	"playa_sunrise": "http://i.imgur.com/TS3VvaJ.jpg",
	"previews": "http://i.imgur.com/wfMRnJW.jpg",
	"riverroad": "http://i.imgur.com/MIoWXLl.jpg",
	"shipyard": "http://i.imgur.com/keeXg0b.jpg",
	"shop": "http://i.imgur.com/eNlS0PI.jpg",
	"showplace": "http://i.imgur.com/LKr8HxV.jpg",
	"showroom": "http://i.imgur.com/9t89syZ.jpg",
	"snow_machine": "http://i.imgur.com/OvDSxbK.jpg",
	"studio_black": "http://i.imgur.com/QIhQLdW.jpg",
	"studio_concrete": "http://i.imgur.com/r2xr714.jpg",
	"studio_smoke": "http://i.imgur.com/68BuylE.jpg",
	"sunset": "http://i.imgur.com/Omw0TAU.jpg",
	"underpass": "http://i.imgur.com/stdkz8q.jpg",
	"white_showroom": "http://i.imgur.com/imGh4NY.jpg",
	"workshop": "http://i.imgur.com/4vD0ZBt.jpg"
}